{"version": 0.6, "generator": "Overpass API 0.7.62.1 084b4234", "osm3s": {"timestamp_osm_base": "2024-04-21T02:40:08Z", "copyright": "The data included in this document is from www.openstreetmap.org. The data is made available under ODbL."}, "elements": [{"type": "node", "id": 1820490038, "lat": 37.5291599, "lon": 71.5045948, "tags": {"addr:city": "Khorog", "addr:housenumber": "56", "addr:postcode": "736000", "addr:street": "Safarmamad street", "amenity": "marketplace", "name": "Ajam Inn", "name:en": "Afghan bazar", "operator": "Ajam Inn"}}, {"type": "node", "id": 1843229165, "lat": 37.4911681, "lon": 71.5268592}, {"type": "node", "id": 1843229167, "lat": 37.4911722, "lon": 71.5266653}, {"type": "node", "id": 1843229196, "lat": 37.4913131, "lon": 71.5268642}, {"type": "node", "id": 1843229198, "lat": 37.4913173, "lon": 71.5266703}, {"type": "node", "id": 4421499317, "lat": 37.4911126, "lon": 71.5387067, "tags": {"name": "\u0422\u0426 \u041f\u0430\u043c\u0438\u0440 \u043f\u043b\u0430\u0437\u0430", "shop": "supermarket"}}, {"type": "node", "id": 4421519601, "lat": 37.4905004, "lon": 71.5375441, "tags": {"shop": "greengrocer"}}, {"type": "node", "id": 4441577072, "lat": 37.4872023, "lon": 71.5341444}, {"type": "node", "id": 4441577073, "lat": 37.4869499, "lon": 71.5341592}, {"type": "node", "id": 4441577074, "lat": 37.4869514, "lon": 71.5342786}, {"type": "node", "id": 4441577075, "lat": 37.4871967, "lon": 71.5342593}, {"type": "node", "id": 4448715514, "lat": 37.5297442, "lon": 71.5041112}, {"type": "node", "id": 4448715515, "lat": 37.5299747, "lon": 71.5047718}, {"type": "node", "id": 4448715516, "lat": 37.5303926, "lon": 71.5037515}, {"type": "node", "id": 4448715517, "lat": 37.5306231, "lon": 71.5044121}, {"type": "node", "id": 5906659848, "lat": 37.4915376, "lon": 71.5423658}, {"type": "node", "id": 5906659849, "lat": 37.4915457, "lon": 71.5424674}, {"type": "node", "id": 5906659850, "lat": 37.4915199, "lon": 71.5424715}, {"type": "node", "id": 5906659851, "lat": 37.4915102, "lon": 71.5423638}, {"type": "node", "id": 6813431486, "lat": 37.5279131, "lon": 71.5049586, "tags": {"name": "Afghan border bazaar", "name:en": "Afghan border bazaar", "opening_hours": "Sa 08:00-12:00", "shop": "supermarket"}}, {"type": "way", "id": 173527769, "nodes": [1843229198, 1843229196, 1843229165, 1843229167, 1843229198], "tags": {"building": "yes", "name:en": "Supermarket Saodat", "shop": "supermarket", "source": "QuickBird 20/04/2010"}}, {"type": "way", "id": 446944081, "nodes": [4441577072, 4441577073, 4441577074, 4441577075, 4441577072], "tags": {"addr:city": "Khorog", "addr:street": "S.Abdurahmon", "building": "yes", "name": "Atlatnika", "shop": "supermarket"}}, {"type": "way", "id": 447808456, "nodes": [4448715515, 4448715514, 4448715516, 4448715517, 4448715515], "tags": {"amenity": "marketplace", "name": "Cross Border Market with Afghanistan", "opening_hours": "Sa 08:30-12:30", "organic": "no"}}, {"type": "way", "id": 625593063, "nodes": [5906659848, 5906659849, 5906659850, 5906659851, 5906659848], "tags": {"addr:city": "Khorog", "addr:housenumber": "113", "addr:postcode": "736000", "addr:street": "\u043a\u04ef\u0447\u0430\u0438 \u041b\u0435\u043d\u0438\u043d", "building": "yes", "ele": "2085", "level": "1", "name": "Mehrafruz", "opening_hours": "24/7", "shop": "supermarket"}}]}